[
  {
    "id": "lead-001",
    "name": "Jason Miller",
    "company": "ChainForge",
    "title": "Growth Lead",
    "platform": "x",
    "leadScore": 92,
    "intentLevel": "high",
    "tags": ["钱包增长", "代理合作", "美国"],
    "region": "San Francisco, US",
    "industry": "Web3 Marketing",
    "followersOrCompanySize": "12k followers",
    "contact": {
      "email": "jason@chainforge.io",
      "x": "@jasonbuilds"
    },
    "sourceUrl": "https://x.com/jasonbuilds/status/190801",
    "snippet": "正在寻找能够稳定提供高质量 crypto 用户线索的数据合作方。",
    "capturedAt": "2026-04-05T08:30:00.000Z",
    "status": "deposited",
    "statusUpdatedAt": "2026-04-05T10:00:00.000Z",
    "destination": "th_team",
    "owner": "Amy",
    "nextFollowUpAt": "2026-04-07T03:00:00.000Z",
    "notes": "已进入成交阶段。"
  },
  {
    "id": "lead-002",
    "name": "Lena Schmidt",
    "company": "NodePilot",
    "title": "Partnership Manager",
    "platform": "linkedin",
    "leadScore": 86,
    "intentLevel": "high",
    "tags": ["B2B", "节点服务", "欧洲"],
    "region": "Berlin, DE",
    "industry": "Infrastructure",
    "followersOrCompanySize": "80 employees",
    "contact": {
      "linkedin": "linkedin.com/in/lena-schmidt"
    },
    "sourceUrl": "https://linkedin.com/in/lena-schmidt",
    "snippet": "对外发布合作需求，重点关注机构客户拓展和 lead enrichment。",
    "capturedAt": "2026-04-03T10:12:00.000Z",
    "status": "account_opened",
    "statusUpdatedAt": "2026-04-04T02:00:00.000Z",
    "destination": "my_team",
    "owner": "Bruce",
    "nextFollowUpAt": "2026-04-08T01:00:00.000Z",
    "notes": "开户推进顺利。"
  },
  {
    "id": "lead-003",
    "name": "Sofia Chen",
    "company": "AlphaMint",
    "title": "Community Director",
    "platform": "telegram",
    "leadScore": 78,
    "intentLevel": "medium",
    "tags": ["社群增长", "NFT", "东南亚"],
    "region": "Singapore",
    "industry": "NFT Platform",
    "followersOrCompanySize": "35k community members",
    "contact": {
      "telegram": "@sofia_community"
    },
    "sourceUrl": "https://t.me/alphamint",
    "snippet": "正在调研高转化的社群增长渠道，关注中文市场转化。",
    "capturedAt": "2026-04-02T04:20:00.000Z",
    "status": "community",
    "statusUpdatedAt": "2026-04-03T09:30:00.000Z",
    "destination": "hk_team",
    "owner": "Amy",
    "nextFollowUpAt": "2026-04-06T09:00:00.000Z",
    "notes": "已拉入社区待持续培育。"
  },
  {
    "id": "lead-004",
    "name": "Derek Hall",
    "company": "VaultNet",
    "title": "Head of BD",
    "platform": "discord",
    "leadScore": 83,
    "intentLevel": "high",
    "tags": ["托管", "机构客户", "RWA"],
    "region": "New York, US",
    "industry": "Custody",
    "followersOrCompanySize": "220 employees",
    "contact": {
      "email": "derek@vaultnet.com",
      "telegram": "@vault_derek"
    },
    "sourceUrl": "https://discord.gg/vaultnet",
    "snippet": "在 Discord AMA 中提到希望补充机构客户来源和销售线索。",
    "capturedAt": "2026-03-31T15:45:00.000Z",
    "status": "reached",
    "statusUpdatedAt": "2026-04-02T03:20:00.000Z",
    "destination": "id_team",
    "owner": "Ken",
    "nextFollowUpAt": "2026-04-06T02:00:00.000Z",
    "notes": "已触达，等待下一步。"
  },
  {
    "id": "lead-005",
    "name": "Maya Patel",
    "company": "YieldSpring",
    "title": "Marketing Ops",
    "platform": "website",
    "leadScore": 67,
    "intentLevel": "medium",
    "tags": ["官网表单", "归因分析"],
    "region": "London, UK",
    "industry": "DeFi",
    "followersOrCompanySize": "40 employees",
    "contact": {
      "email": "maya@yieldspring.xyz"
    },
    "sourceUrl": "https://yieldspring.xyz/contact",
    "snippet": "官网团队页新增增长招聘，侧面说明正在搭建 lead generation 流程。",
    "capturedAt": "2026-03-29T11:30:00.000Z",
    "status": "registered",
    "statusUpdatedAt": "2026-03-31T08:00:00.000Z",
    "destination": "vn_team",
    "owner": "Bruce",
    "nextFollowUpAt": "2026-04-10T08:00:00.000Z",
    "notes": "已完成注册。"
  },
  {
    "id": "lead-006",
    "name": "Noah Garcia",
    "company": "",
    "title": "Founder",
    "platform": "x",
    "leadScore": 58,
    "intentLevel": "low",
    "tags": ["早期项目", "Meme"],
    "region": "Miami, US",
    "industry": "Consumer Crypto",
    "followersOrCompanySize": "4.5k followers",
    "contact": {
      "x": "@noahonchain"
    },
    "sourceUrl": "https://x.com/noahonchain/status/190554",
    "snippet": "仅表达对获客感兴趣，但尚未说明预算和时点。",
    "capturedAt": "2026-03-24T07:10:00.000Z",
    "status": "assigned",
    "statusUpdatedAt": "2026-03-25T01:15:00.000Z",
    "destination": "ai_outreach",
    "owner": "AI Agent",
    "notes": "先由 AI 完成首轮触达。"
  },
  {
    "id": "lead-007",
    "name": "Ari Tan",
    "company": "BlockBridge",
    "title": "Regional GM",
    "platform": "linkedin",
    "leadScore": 88,
    "intentLevel": "high",
    "tags": ["亚洲市场", "支付", "机构"],
    "region": "Hong Kong",
    "industry": "Payments",
    "followersOrCompanySize": "300 employees",
    "contact": {
      "email": "ari@blockbridge.io",
      "linkedin": "linkedin.com/in/ari-tan"
    },
    "sourceUrl": "https://linkedin.com/in/ari-tan",
    "snippet": "提到正在扩张亚太机构销售团队，需要高质量潜在客户名单。",
    "capturedAt": "2026-03-22T09:00:00.000Z",
    "status": "account_opened",
    "statusUpdatedAt": "2026-03-28T06:45:00.000Z",
    "destination": "za_team",
    "owner": "Ken",
    "nextFollowUpAt": "2026-04-09T06:00:00.000Z",
    "notes": "区域重点项目。"
  },
  {
    "id": "lead-008",
    "name": "Olivia Brooks",
    "company": "LumaChain",
    "title": "Product Marketing Manager",
    "platform": "telegram",
    "leadScore": 72,
    "intentLevel": "medium",
    "tags": ["钱包", "活动投放"],
    "region": "Toronto, CA",
    "industry": "Wallet",
    "followersOrCompanySize": "18k telegram subscribers",
    "contact": {
      "telegram": "@olivia_luma"
    },
    "sourceUrl": "https://t.me/lumachainofficial",
    "snippet": "询问如何获得更高净值钱包用户线索。",
    "capturedAt": "2026-03-18T12:40:00.000Z",
    "status": "community",
    "statusUpdatedAt": "2026-03-21T04:10:00.000Z",
    "destination": "ai_outreach",
    "owner": "AI Agent",
    "nextFollowUpAt": "2026-04-11T04:00:00.000Z",
    "notes": "AI 首轮触达后已进入社区。"
  },
  {
    "id": "lead-009",
    "name": "Marcus Reed",
    "company": "ProtoLayer",
    "title": "BD Associate",
    "platform": "discord",
    "leadScore": 64,
    "intentLevel": "medium",
    "tags": ["开发者生态", "黑客松"],
    "region": "Austin, US",
    "industry": "L2",
    "followersOrCompanySize": "120 employees",
    "contact": {
      "email": "marcus@protolayer.dev"
    },
    "sourceUrl": "https://discord.gg/protolayer",
    "snippet": "在开发者活动频道中公开征集合适的合作推广渠道。",
    "capturedAt": "2026-03-15T06:20:00.000Z",
    "status": "reached",
    "statusUpdatedAt": "2026-03-18T07:10:00.000Z",
    "destination": "th_team",
    "owner": "Ken",
    "notes": "已进入销售对话。"
  },
  {
    "id": "lead-010",
    "name": "Emma Rossi",
    "company": "SignalStack",
    "title": "Revenue Lead",
    "platform": "website",
    "leadScore": 91,
    "intentLevel": "high",
    "tags": ["SaaS", "销售线索", "机构订阅"],
    "region": "Milan, IT",
    "industry": "Web3 SaaS",
    "followersOrCompanySize": "60 employees",
    "contact": {
      "email": "emma@signalstack.ai"
    },
    "sourceUrl": "https://signalstack.ai/request-demo",
    "snippet": "官网 demo 表单中提到需要高质量出海线索与自动化 enrich 服务。",
    "capturedAt": "2026-03-12T14:00:00.000Z",
    "status": "deposited",
    "statusUpdatedAt": "2026-03-20T12:00:00.000Z",
    "destination": "my_team",
    "owner": "Amy",
    "nextFollowUpAt": "2026-04-06T07:30:00.000Z",
    "notes": "成交优先级极高。"
  },
  {
    "id": "lead-011",
    "name": "Yuki Sato",
    "company": "OrbitX",
    "title": "",
    "platform": "x",
    "leadScore": 74,
    "intentLevel": "medium",
    "tags": ["日本市场", "社区扩张"],
    "region": "Tokyo, JP",
    "industry": "Exchange",
    "followersOrCompanySize": "22k followers",
    "contact": {
      "x": "@yuki_orbitx"
    },
    "sourceUrl": "https://x.com/yuki_orbitx/status/190112",
    "snippet": "多次提到希望寻找新的市场拓展合作方。",
    "capturedAt": "2026-03-10T03:15:00.000Z",
    "status": "assigned",
    "statusUpdatedAt": "2026-03-11T02:30:00.000Z",
    "destination": "hk_team",
    "owner": "Ken",
    "nextFollowUpAt": "2026-04-12T01:00:00.000Z",
    "notes": "待香港团队跟进。"
  },
  {
    "id": "lead-012",
    "name": "Priya Nair",
    "company": "Credora Labs",
    "title": "Chief of Staff",
    "platform": "linkedin",
    "leadScore": 81,
    "intentLevel": "high",
    "tags": ["信用评分", "机构 BD"],
    "region": "Dubai, UAE",
    "industry": "Risk & Analytics",
    "followersOrCompanySize": "95 employees",
    "contact": {
      "linkedin": "linkedin.com/in/priyanair",
      "email": "priya@credoralabs.com"
    },
    "sourceUrl": "https://linkedin.com/in/priyanair",
    "snippet": "发帖征询新的机构合作来源，明显处于 pipeline 扩张阶段。",
    "capturedAt": "2026-03-08T05:40:00.000Z",
    "status": "registered",
    "statusUpdatedAt": "2026-03-14T05:20:00.000Z",
    "destination": "ai_outreach",
    "owner": "AI Agent",
    "nextFollowUpAt": "2026-04-07T05:00:00.000Z",
    "notes": "AI 触达后注册转化表现较好。"
  }
]
